triple_quote_clean/__init__.py
triple_quote_clean/_jinja_pipe.py
triple_quote_clean/_pipe.py
triple_quote_clean/_triple_quote_clean.py
triple_quote_clean-1.1.0.dist-info/LICENSE.txt
triple_quote_clean-1.1.0.dist-info/METADATA
triple_quote_clean-1.1.0.dist-info/WHEEL
triple_quote_clean-1.1.0.dist-info/top_level.txt
triple_quote_clean-1.1.0.dist-info/RECORD
