Metadata-Version: 2.1
Name: triple-quote-clean
Version: 1.1.0
Summary: clean up triple quotes
Author-email: Chris <chrisam1993@live.com>
Project-URL: Homepage, https://github.com/Chr1sC0de/triple-quote-clean
Project-URL: Bug Tracker, https://github.com/Chr1sC0de/triple-quote-clean/issues
Classifier: License :: OSI Approved :: MIT License
Classifier: Programming Language :: Python
Classifier: Programming Language :: Python :: 3.7
Classifier: Programming Language :: Python :: 3.8
Classifier: Programming Language :: Python :: 3.9
Classifier: Programming Language :: Python :: 3.10
Classifier: Programming Language :: Python :: 3.11
Requires-Python: >=3.7
License-File: LICENSE.txt
Requires-Dist: jinja2
